[

{"key": "Test1", "alreadyUsed": false, "email": "", "firstName": "", "lastName": ""},

{"key": "Test2", "alreadyUsed": false, "email": "", "firstName": "", "lastName": ""},

{"key": "Test3", "alreadyUsed": false, "email": "", "firstName": "", "lastName": ""},

{"key": "Test4", "alreadyUsed": false, "email": "", "firstName": "", "lastName": ""},

{"key": "Test5", "alreadyUsed": false, "email": "", "firstName": "", "lastName": ""},

{"key": "Test6", "alreadyUsed": false, "email": "", "firstName": "", "lastName": ""},

{"key": "Test7", "alreadyUsed": false, "email": "", "firstName": "", "lastName": ""},

{"key": "Test8", "alreadyUsed": false, "email": "", "firstName": "", "lastName": ""},

{"key": "Test9", "alreadyUsed": false, "email": "", "firstName": "", "lastName": ""},

{"key": "Test10", "alreadyUsed": false, "email": "", "firstName": "", "lastName": ""},

{"key": "Test11", "alreadyUsed": false, "email": "", "firstName": "", "lastName": ""},

{"key": "Test12", "alreadyUsed": false, "email": "", "firstName": "", "lastName": ""},

{"key": "Test13", "alreadyUsed": false, "email": "", "firstName": "", "lastName": ""},

{"key": "Test14", "alreadyUsed": false, "email": "", "firstName": "", "lastName": ""},

{"key": "Test15", "alreadyUsed": false, "email": "", "firstName": "", "lastName": ""},

{"key": "Test16", "alreadyUsed": false, "email": "", "firstName": "", "lastName": ""},

{"key": "Test17", "alreadyUsed": false, "email": "", "firstName": "", "lastName": ""},

{"key": "Test18", "alreadyUsed": false, "email": "", "firstName": "", "lastName": ""},

{"key": "Test19", "alreadyUsed": false, "email": "", "firstName": "", "lastName": ""},

{"key": "Test20", "alreadyUsed": false, "email": "", "firstName": "", "lastName": ""},

{"key": "Test21", "alreadyUsed": false, "email": "", "firstName": "", "lastName": ""},

{"key": "Test22", "alreadyUsed": false, "email": "", "firstName": "", "lastName": ""},

{"key": "Test23", "alreadyUsed": false, "email": "", "firstName": "", "lastName": ""},

{"key": "Test24", "alreadyUsed": false, "email": "", "firstName": "", "lastName": ""},

{"key": "Test25", "alreadyUsed": false, "email": "", "firstName": "", "lastName": ""},

{"key": "iNqhTt7MrH", "alreadyUsed": false, "email": "", "firstName": "", "lastName": ""},

{"key": "FNsWV8WREn", "alreadyUsed": false, "email": "", "firstName": "", "lastName": ""},

{"key": "MmXAlyVWOv", "alreadyUsed": false, "email": "", "firstName": "", "lastName": ""},

{"key": "HipINp167m", "alreadyUsed": false, "email": "", "firstName": "", "lastName": ""},

{"key": "GsNkLqBxZE", "alreadyUsed": false, "email": "", "firstName": "", "lastName": ""},

{"key": "w6dpQSaBLH", "alreadyUsed": false, "email": "", "firstName": "", "lastName": ""},

{"key": "EUH1jDcVNP", "alreadyUsed": false, "email": "", "firstName": "", "lastName": ""},

{"key": "wVwioFTH8D", "alreadyUsed": false, "email": "", "firstName": "", "lastName": ""},

{"key": "9AQ9Dlu0Kj", "alreadyUsed": false, "email": "", "firstName": "", "lastName": ""},

{"key": "xOifPpax4Y", "alreadyUsed": false, "email": "", "firstName": "", "lastName": ""},

{"key": "dHRNWTGvyb", "alreadyUsed": false, "email": "", "firstName": "", "lastName": ""},

{"key": "A8MpF0lCIG", "alreadyUsed": false, "email": "", "firstName": "", "lastName": ""},

{"key": "Rk3HJ5R24D", "alreadyUsed": false, "email": "", "firstName": "", "lastName": ""},

{"key": "hGLEphYFPP", "alreadyUsed": false, "email": "", "firstName": "", "lastName": ""},

{"key": "8y3WNjw451", "alreadyUsed": false, "email": "", "firstName": "", "lastName": ""},

{"key": "SqIA0m7oZh", "alreadyUsed": false, "email": "", "firstName": "", "lastName": ""},

{"key": "kq51awIP6m", "alreadyUsed": false, "email": "", "firstName": "", "lastName": ""},

{"key": "fOhSZ4spg9", "alreadyUsed": false, "email": "", "firstName": "", "lastName": ""},

{"key": "qeZo8uwpnm", "alreadyUsed": false, "email": "", "firstName": "", "lastName": ""},

{"key": "3GiOup5uus", "alreadyUsed": false, "email": "", "firstName": "", "lastName": ""},

{"key": "KMB09kEChC", "alreadyUsed": false, "email": "", "firstName": "", "lastName": ""},

{"key": "EaizlRF7vz", "alreadyUsed": false, "email": "", "firstName": "", "lastName": ""},

{"key": "cfK3RY8vId", "alreadyUsed": false, "email": "", "firstName": "", "lastName": ""},

{"key": "RekFjl9aEa", "alreadyUsed": false, "email": "", "firstName": "", "lastName": ""},

{"key": "CgEimD0FyC", "alreadyUsed": false, "email": "", "firstName": "", "lastName": ""},

{"key": "LDCA9OsNII", "alreadyUsed": false, "email": "", "firstName": "", "lastName": ""},

{"key": "9qVFVcVBlB", "alreadyUsed": false, "email": "", "firstName": "", "lastName": ""},

{"key": "V6ePfTlwVg", "alreadyUsed": false, "email": "", "firstName": "", "lastName": ""},

{"key": "wUHimKLJsK", "alreadyUsed": false, "email": "", "firstName": "", "lastName": ""},

{"key": "9HNCtMJIw4", "alreadyUsed": false, "email": "", "firstName": "", "lastName": ""},

{"key": "tmCtXj4tEJ", "alreadyUsed": false, "email": "", "firstName": "", "lastName": ""},

{"key": "X06PwLymyW", "alreadyUsed": false, "email": "", "firstName": "", "lastName": ""},

{"key": "79Qrd3k7Tx", "alreadyUsed": false, "email": "", "firstName": "", "lastName": ""},

{"key": "428hPavnLe", "alreadyUsed": false, "email": "", "firstName": "", "lastName": ""},

{"key": "qL2dHtQZ31", "alreadyUsed": false, "email": "", "firstName": "", "lastName": ""},

{"key": "6BtrQUKZED", "alreadyUsed": false, "email": "", "firstName": "", "lastName": ""},

{"key": "fOcBtnlIWw", "alreadyUsed": false, "email": "", "firstName": "", "lastName": ""},

{"key": "J1Mzl02Qr7", "alreadyUsed": false, "email": "", "firstName": "", "lastName": ""},

{"key": "XNOI5urgvm", "alreadyUsed": false, "email": "", "firstName": "", "lastName": ""},

{"key": "5kGafxCrjH", "alreadyUsed": false, "email": "", "firstName": "", "lastName": ""},

{"key": "HEhmzbw4VK", "alreadyUsed": false, "email": "", "firstName": "", "lastName": ""},

{"key": "xNA7y3edbx", "alreadyUsed": false, "email": "", "firstName": "", "lastName": ""},

{"key": "a5IqAPv9cE", "alreadyUsed": false, "email": "", "firstName": "", "lastName": ""},

{"key": "9Ziy7LIFKF", "alreadyUsed": false, "email": "", "firstName": "", "lastName": ""},

{"key": "w8KRAmiUt7", "alreadyUsed": false, "email": "", "firstName": "", "lastName": ""},

{"key": "nfLBB7eeT6", "alreadyUsed": false, "email": "", "firstName": "", "lastName": ""},

{"key": "DI6BKHwQEo", "alreadyUsed": false, "email": "", "firstName": "", "lastName": ""},

{"key": "ovFRr13kcH", "alreadyUsed": false, "email": "", "firstName": "", "lastName": ""},

{"key": "45xMNgDOv5", "alreadyUsed": false, "email": "", "firstName": "", "lastName": ""},

{"key": "tatC8xypDe", "alreadyUsed": false, "email": "", "firstName": "", "lastName": ""},

{"key": "RlAQwo8Vfa", "alreadyUsed": false, "email": "", "firstName": "", "lastName": ""},

{"key": "nkLYPeZqbB", "alreadyUsed": false, "email": "", "firstName": "", "lastName": ""},

{"key": "xmJOZHp5Fs", "alreadyUsed": false, "email": "", "firstName": "", "lastName": ""},

{"key": "tj9jyeOMXs", "alreadyUsed": false, "email": "", "firstName": "", "lastName": ""},

{"key": "6SonKlCEH0", "alreadyUsed": false, "email": "", "firstName": "", "lastName": ""},

{"key": "5lY7L7vyG9", "alreadyUsed": false, "email": "", "firstName": "", "lastName": ""},

{"key": "rSXSc4x132", "alreadyUsed": false, "email": "", "firstName": "", "lastName": ""},

{"key": "aubMebGgFg", "alreadyUsed": false, "email": "", "firstName": "", "lastName": ""},

{"key": "HS9PANuBHY", "alreadyUsed": false, "email": "", "firstName": "", "lastName": ""},

{"key": "GFfZcTISpb", "alreadyUsed": false, "email": "", "firstName": "", "lastName": ""},

{"key": "zKpyQ4rOIs", "alreadyUsed": false, "email": "", "firstName": "", "lastName": ""},

{"key": "0Hwxll1raV", "alreadyUsed": false, "email": "", "firstName": "", "lastName": ""},

{"key": "a1VOXp1DlA", "alreadyUsed": false, "email": "", "firstName": "", "lastName": ""},

{"key": "8DtvqbZ4Tu", "alreadyUsed": false, "email": "", "firstName": "", "lastName": ""},

{"key": "qn8OBj0TUE", "alreadyUsed": false, "email": "", "firstName": "", "lastName": ""},

{"key": "vdVh8A6tTK", "alreadyUsed": false, "email": "", "firstName": "", "lastName": ""},

{"key": "95FvABiTQ4", "alreadyUsed": false, "email": "", "firstName": "", "lastName": ""},

{"key": "N86DHrQtG2", "alreadyUsed": false, "email": "", "firstName": "", "lastName": ""},

{"key": "ilpLzdpLA8", "alreadyUsed": false, "email": "", "firstName": "", "lastName": ""},

{"key": "Ve5SdcEkl9", "alreadyUsed": false, "email": "", "firstName": "", "lastName": ""},

{"key": "w1r9wn9GEU", "alreadyUsed": false, "email": "", "firstName": "", "lastName": ""},

{"key": "x8lsAhftQB", "alreadyUsed": false, "email": "", "firstName": "", "lastName": ""},

{"key": "J1NHfMS6LF", "alreadyUsed": false, "email": "", "firstName": "", "lastName": ""},

{"key": "5glgoapwf4", "alreadyUsed": false, "email": "", "firstName": "", "lastName": ""},

{"key": "v3i5VQMngI", "alreadyUsed": false, "email": "", "firstName": "", "lastName": ""},

{"key": "VwAFcLw4ky", "alreadyUsed": false, "email": "", "firstName": "", "lastName": ""},

{"key": "6R8ASyknxl", "alreadyUsed": false, "email": "", "firstName": "", "lastName": ""},

{"key": "YCFVNtkPHH", "alreadyUsed": false, "email": "", "firstName": "", "lastName": ""},

{"key": "9BfrcahoSM", "alreadyUsed": false, "email": "", "firstName": "", "lastName": ""},

{"key": "ED6JG6HxGi", "alreadyUsed": false, "email": "", "firstName": "", "lastName": ""},

{"key": "Ctz4gPwIiW", "alreadyUsed": false, "email": "", "firstName": "", "lastName": ""},

{"key": "r52t3ESjdo", "alreadyUsed": false, "email": "", "firstName": "", "lastName": ""},

{"key": "0Xyp9skTB1", "alreadyUsed": false, "email": "", "firstName": "", "lastName": ""},

{"key": "3r0S6Gcit4", "alreadyUsed": false, "email": "", "firstName": "", "lastName": ""},

{"key": "JprLYGgBKd", "alreadyUsed": false, "email": "", "firstName": "", "lastName": ""},

{"key": "WXxKRut5o9", "alreadyUsed": false, "email": "", "firstName": "", "lastName": ""},

{"key": "UuixL6HV5S", "alreadyUsed": false, "email": "", "firstName": "", "lastName": ""},

{"key": "JnjJ2kdsGh", "alreadyUsed": false, "email": "", "firstName": "", "lastName": ""},

{"key": "STL21rknw5", "alreadyUsed": false, "email": "", "firstName": "", "lastName": ""},

{"key": "9GsxkfBWSl", "alreadyUsed": false, "email": "", "firstName": "", "lastName": ""},

{"key": "4W5JfOrrDm", "alreadyUsed": false, "email": "", "firstName": "", "lastName": ""},

{"key": "r1ZrY3TNu5", "alreadyUsed": false, "email": "", "firstName": "", "lastName": ""},

{"key": "AopXM4oGJb", "alreadyUsed": false, "email": "", "firstName": "", "lastName": ""},

{"key": "0kzT9q4eGa", "alreadyUsed": false, "email": "", "firstName": "", "lastName": ""},

{"key": "G21vod7Cmi", "alreadyUsed": false, "email": "", "firstName": "", "lastName": ""},

{"key": "QUQRz3rtHq", "alreadyUsed": false, "email": "", "firstName": "", "lastName": ""},

{"key": "ZbKqzjnf6R", "alreadyUsed": false, "email": "", "firstName": "", "lastName": ""},

{"key": "azBvoAPue7", "alreadyUsed": false, "email": "", "firstName": "", "lastName": ""},

{"key": "GPQfBtbZJ2", "alreadyUsed": false, "email": "", "firstName": "", "lastName": ""},

{"key": "3YSGNMvaqB", "alreadyUsed": false, "email": "", "firstName": "", "lastName": ""},

{"key": "ij7xu6qGTV", "alreadyUsed": false, "email": "", "firstName": "", "lastName": ""},

{"key": "SzdJmMtxnz", "alreadyUsed": false, "email": "", "firstName": "", "lastName": ""},

{"key": "WX0MZJRBUB", "alreadyUsed": false, "email": "", "firstName": "", "lastName": ""},

{"key": "lZpuXCzjxw", "alreadyUsed": false, "email": "", "firstName": "", "lastName": ""},

{"key": "c0a56SzNT3", "alreadyUsed": false, "email": "", "firstName": "", "lastName": ""},

{"key": "Ss3lPKWo9m", "alreadyUsed": false, "email": "", "firstName": "", "lastName": ""},

{"key": "X0GQ8GcMFh", "alreadyUsed": false, "email": "", "firstName": "", "lastName": ""},

{"key": "96dqQkt7rU", "alreadyUsed": false, "email": "", "firstName": "", "lastName": ""},

{"key": "9drBpi4DYA", "alreadyUsed": false, "email": "", "firstName": "", "lastName": ""},

{"key": "GE1NmvdRHB", "alreadyUsed": false, "email": "", "firstName": "", "lastName": ""},

{"key": "BHhvOi9eZ8", "alreadyUsed": false, "email": "", "firstName": "", "lastName": ""},

{"key": "dfDwkXkKwr", "alreadyUsed": false, "email": "", "firstName": "", "lastName": ""},

{"key": "s8k0q6IayQ", "alreadyUsed": false, "email": "", "firstName": "", "lastName": ""},

{"key": "NtSo3PJn1Y", "alreadyUsed": false, "email": "", "firstName": "", "lastName": ""},

{"key": "7IF6a19eEA", "alreadyUsed": false, "email": "", "firstName": "", "lastName": ""},

{"key": "fkuGaTiPr3", "alreadyUsed": false, "email": "", "firstName": "", "lastName": ""},

{"key": "4dMXheOjM2", "alreadyUsed": false, "email": "", "firstName": "", "lastName": ""},

{"key": "WqWPRLl0dz", "alreadyUsed": false, "email": "", "firstName": "", "lastName": ""},

{"key": "yqB9SqsCMi", "alreadyUsed": false, "email": "", "firstName": "", "lastName": ""},

{"key": "IV0qWIwD30", "alreadyUsed": false, "email": "", "firstName": "", "lastName": ""},

{"key": "6jOWYWvnFq", "alreadyUsed": false, "email": "", "firstName": "", "lastName": ""},

{"key": "YQaZr4ECVE", "alreadyUsed": false, "email": "", "firstName": "", "lastName": ""},

{"key": "UidNNqcbuE", "alreadyUsed": false, "email": "", "firstName": "", "lastName": ""},

{"key": "9T93L3SMSH", "alreadyUsed": false, "email": "", "firstName": "", "lastName": ""},

{"key": "IHFAPQVM4y", "alreadyUsed": false, "email": "", "firstName": "", "lastName": ""},

{"key": "6jY4hj6EfS", "alreadyUsed": false, "email": "", "firstName": "", "lastName": ""},

{"key": "oVspffI6Wj", "alreadyUsed": false, "email": "", "firstName": "", "lastName": ""},

{"key": "WFT2LNjK9G", "alreadyUsed": false, "email": "", "firstName": "", "lastName": ""},

{"key": "DiLG3Wc6L3", "alreadyUsed": false, "email": "", "firstName": "", "lastName": ""},

{"key": "CWDnefxnsL", "alreadyUsed": false, "email": "", "firstName": "", "lastName": ""},

{"key": "tFAxFITRcl", "alreadyUsed": false, "email": "", "firstName": "", "lastName": ""},

{"key": "lJXtUYW32y", "alreadyUsed": false, "email": "", "firstName": "", "lastName": ""},

{"key": "46BDj5D9Jc", "alreadyUsed": false, "email": "", "firstName": "", "lastName": ""},

{"key": "Yi7I6763pE", "alreadyUsed": false, "email": "", "firstName": "", "lastName": ""},

{"key": "qqmPPUI3JN", "alreadyUsed": false, "email": "", "firstName": "", "lastName": ""},

{"key": "fUcI2lnRV9", "alreadyUsed": false, "email": "", "firstName": "", "lastName": ""},

{"key": "HjDFJI6MBw", "alreadyUsed": false, "email": "", "firstName": "", "lastName": ""},

{"key": "Afxhz6jmLZ", "alreadyUsed": false, "email": "", "firstName": "", "lastName": ""},

{"key": "uDsu26hl4q", "alreadyUsed": false, "email": "", "firstName": "", "lastName": ""},

{"key": "7iALUtIGpU", "alreadyUsed": false, "email": "", "firstName": "", "lastName": ""},

{"key": "4KgrhMSLp1", "alreadyUsed": false, "email": "", "firstName": "", "lastName": ""},

{"key": "wvaZYTML5U", "alreadyUsed": false, "email": "", "firstName": "", "lastName": ""},

{"key": "fBSS4ApBUX", "alreadyUsed": false, "email": "", "firstName": "", "lastName": ""},

{"key": "5PVcxJtvyx", "alreadyUsed": false, "email": "", "firstName": "", "lastName": ""},

{"key": "g5VdkxyqNR", "alreadyUsed": false, "email": "", "firstName": "", "lastName": ""},

{"key": "LUqOi0x271", "alreadyUsed": false, "email": "", "firstName": "", "lastName": ""},

{"key": "er1IN7O9uL", "alreadyUsed": false, "email": "", "firstName": "", "lastName": ""},

{"key": "xBp20gVfJx", "alreadyUsed": false, "email": "", "firstName": "", "lastName": ""},

{"key": "bUaOF4G5Gb", "alreadyUsed": false, "email": "", "firstName": "", "lastName": ""},

{"key": "HRF48p1Bh7", "alreadyUsed": false, "email": "", "firstName": "", "lastName": ""},

{"key": "WbJMnFaCWL", "alreadyUsed": false, "email": "", "firstName": "", "lastName": ""},

{"key": "9VFz6yeSJ6", "alreadyUsed": false, "email": "", "firstName": "", "lastName": ""},

{"key": "pUFXvoMjtG", "alreadyUsed": false, "email": "", "firstName": "", "lastName": ""},

{"key": "yl8Nw1C3ea", "alreadyUsed": false, "email": "", "firstName": "", "lastName": ""},

{"key": "35pwthN446", "alreadyUsed": false, "email": "", "firstName": "", "lastName": ""},

{"key": "mJLAWCUw3r", "alreadyUsed": false, "email": "", "firstName": "", "lastName": ""},

{"key": "st8aIlk02n", "alreadyUsed": false, "email": "", "firstName": "", "lastName": ""},

{"key": "HGAtIO5yDz", "alreadyUsed": false, "email": "", "firstName": "", "lastName": ""},

{"key": "qY7VtFSYBN", "alreadyUsed": false, "email": "", "firstName": "", "lastName": ""},

{"key": "5CRHoqMnUT", "alreadyUsed": false, "email": "", "firstName": "", "lastName": ""},

{"key": "kJoX1I5jYT", "alreadyUsed": false, "email": "", "firstName": "", "lastName": ""},

{"key": "cayDcLIxYq", "alreadyUsed": false, "email": "", "firstName": "", "lastName": ""},

{"key": "Rmg1SdQFjG", "alreadyUsed": false, "email": "", "firstName": "", "lastName": ""},

{"key": "OBi7yLlJGe", "alreadyUsed": false, "email": "", "firstName": "", "lastName": ""},

{"key": "cr8glh6qJa", "alreadyUsed": false, "email": "", "firstName": "", "lastName": ""},

{"key": "5Qdfp4KBcg", "alreadyUsed": false, "email": "", "firstName": "", "lastName": ""},

{"key": "wZYPQLynwU", "alreadyUsed": false, "email": "", "firstName": "", "lastName": ""},

{"key": "pdHeuYG2Se", "alreadyUsed": false, "email": "", "firstName": "", "lastName": ""},

{"key": "pU3wcQFU31", "alreadyUsed": false, "email": "", "firstName": "", "lastName": ""},

{"key": "ou1BuQSEwq", "alreadyUsed": false, "email": "", "firstName": "", "lastName": ""},

{"key": "71bdgHDGCC", "alreadyUsed": false, "email": "", "firstName": "", "lastName": ""},

{"key": "uGWS6KFWRr", "alreadyUsed": false, "email": "", "firstName": "", "lastName": ""},

{"key": "ftfs5EQtUV", "alreadyUsed": false, "email": "", "firstName": "", "lastName": ""},

{"key": "vpRXc6hRhU", "alreadyUsed": false, "email": "", "firstName": "", "lastName": ""},

{"key": "5B3vshUDOU", "alreadyUsed": false, "email": "", "firstName": "", "lastName": ""},

{"key": "2TwBpSnp37", "alreadyUsed": false, "email": "", "firstName": "", "lastName": ""},

{"key": "7CVIaWA3JM", "alreadyUsed": false, "email": "", "firstName": "", "lastName": ""},

{"key": "RX8TFifwoK", "alreadyUsed": false, "email": "", "firstName": "", "lastName": ""},

{"key": "LeSEO8fLWL", "alreadyUsed": false, "email": "", "firstName": "", "lastName": ""},

{"key": "3ccUGPGU49", "alreadyUsed": false, "email": "", "firstName": "", "lastName": ""},

{"key": "WXHd671OFA", "alreadyUsed": false, "email": "", "firstName": "", "lastName": ""},

{"key": "mQHSjjhq2R", "alreadyUsed": false, "email": "", "firstName": "", "lastName": ""},

{"key": "ZbNLtMwngs", "alreadyUsed": false, "email": "", "firstName": "", "lastName": ""},

{"key": "aLzojPc77B", "alreadyUsed": false, "email": "", "firstName": "", "lastName": ""},
{"key": "CeoweVO4iH", "alreadyUsed": false, "email": "", "firstName": "", "lastName": ""},

{"key": "2CsjzDyRqh", "alreadyUsed": false, "email": "", "firstName": "", "lastName": ""},

{"key": "fWpKvYlkJf", "alreadyUsed": false, "email": "", "firstName": "", "lastName": ""},

{"key": "k2s7k9nx3K", "alreadyUsed": false, "email": "", "firstName": "", "lastName": ""},

{"key": "J0kGWpQO5s", "alreadyUsed": false, "email": "", "firstName": "", "lastName": ""},

{"key": "EHsgpmiW5l", "alreadyUsed": false, "email": "", "firstName": "", "lastName": ""},

{"key": "b7Idp9Th5B", "alreadyUsed": false, "email": "", "firstName": "", "lastName": ""},

{"key": "OpmAkhe4ck", "alreadyUsed": false, "email": "", "firstName": "", "lastName": ""},

{"key": "g4gw9YhbKB", "alreadyUsed": false, "email": "", "firstName": "", "lastName": ""},

{"key": "cUMrVmHCCJ", "alreadyUsed": false, "email": "", "firstName": "", "lastName": ""},
{"key": "7SLiT456FO", "alreadyUsed": false, "email": "", "firstName": "", "lastName": ""},

{"key": "GvndJIOm34", "alreadyUsed": false, "email": "", "firstName": "", "lastName": ""},

{"key": "GN3bgrvO9z", "alreadyUsed": false, "email": "", "firstName": "", "lastName": ""},

{"key": "t6U23KPhf0", "alreadyUsed": false, "email": "", "firstName": "", "lastName": ""},

{"key": "Q2JUTCGbfS", "alreadyUsed": false, "email": "", "firstName": "", "lastName": ""},

{"key": "IKu6X7VdJN", "alreadyUsed": false, "email": "", "firstName": "", "lastName": ""},

{"key": "iS8EFH2kmT", "alreadyUsed": false, "email": "", "firstName": "", "lastName": ""},

{"key": "Li0vGG87B1", "alreadyUsed": false, "email": "", "firstName": "", "lastName": ""},

{"key": "q29j82z26j", "alreadyUsed": false, "email": "", "firstName": "", "lastName": ""},

{"key": "GZZzkzeAiC", "alreadyUsed": false, "email": "", "firstName": "", "lastName": ""},

{"key": "TF8GyxxcWh", "alreadyUsed": false, "email": "", "firstName": "", "lastName": ""},

{"key": "hBAzGUVCL8", "alreadyUsed": false, "email": "", "firstName": "", "lastName": ""},

{"key": "07IChRBxZF", "alreadyUsed": false, "email": "", "firstName": "", "lastName": ""},

{"key": "SzKEl9VJQv", "alreadyUsed": false, "email": "", "firstName": "", "lastName": ""},

{"key": "s5jlrKdzmK", "alreadyUsed": false, "email": "", "firstName": "", "lastName": ""},

{"key": "wAItYWnbKE", "alreadyUsed": false, "email": "", "firstName": "", "lastName": ""},

{"key": "xtlXaKh7fj", "alreadyUsed": false, "email": "", "firstName": "", "lastName": ""},

{"key": "BWnVgjikTG", "alreadyUsed": false, "email": "", "firstName": "", "lastName": ""},

{"key": "k2u26ZL7ki", "alreadyUsed": false, "email": "", "firstName": "", "lastName": ""},

{"key": "e72VeXXhfJ", "alreadyUsed": false, "email": "", "firstName": "", "lastName": ""},

{"key": "NmVtazhJL7", "alreadyUsed": false, "email": "", "firstName": "", "lastName": ""},

{"key": "0kjquNzgFT", "alreadyUsed": false, "email": "", "firstName": "", "lastName": ""},

{"key": "jEAffljqrW", "alreadyUsed": false, "email": "", "firstName": "", "lastName": ""},

{"key": "9EewkzyPa7", "alreadyUsed": false, "email": "", "firstName": "", "lastName": ""},

{"key": "sNIn4Uq4Fs", "alreadyUsed": false, "email": "", "firstName": "", "lastName": ""},

{"key": "hHTOPF9mTy", "alreadyUsed": false, "email": "", "firstName": "", "lastName": ""},

{"key": "sgHfuNHd3U", "alreadyUsed": false, "email": "", "firstName": "", "lastName": ""},

{"key": "dXX1t4N3JX", "alreadyUsed": false, "email": "", "firstName": "", "lastName": ""},

{"key": "6Aw0rSsiYU", "alreadyUsed": false, "email": "", "firstName": "", "lastName": ""},

{"key": "5Wdtg8MqIo", "alreadyUsed": false, "email": "", "firstName": "", "lastName": ""},

{"key": "9PhEeV2GRj", "alreadyUsed": false, "email": "", "firstName": "", "lastName": ""},

{"key": "6VBuFWp6xi", "alreadyUsed": false, "email": "", "firstName": "", "lastName": ""},

{"key": "CmNjY05vOo", "alreadyUsed": false, "email": "", "firstName": "", "lastName": ""},

{"key": "N16lnK80pz", "alreadyUsed": false, "email": "", "firstName": "", "lastName": ""},

{"key": "XiN6M5GR7w", "alreadyUsed": false, "email": "", "firstName": "", "lastName": ""},

{"key": "7LeoSh5kik", "alreadyUsed": false, "email": "", "firstName": "", "lastName": ""},

{"key": "vcuqer14tG", "alreadyUsed": false, "email": "", "firstName": "", "lastName": ""},

{"key": "vTBCXHuI2d", "alreadyUsed": false, "email": "", "firstName": "", "lastName": ""},

{"key": "ZKhTd2hWem", "alreadyUsed": false, "email": "", "firstName": "", "lastName": ""},

{"key": "BKWtAHnB8p", "alreadyUsed": false, "email": "", "firstName": "", "lastName": ""}



]